help2man/__init__.py
help2man/__main__.py
help2man/_version.py
help2man/py.typed
help2man/assets/jinja2/template.man.j2
help2man/assets/jinja2/template.md.j2
help2man/assets/txt/description.txt
help2man/assets/txt/epilog.txt
help2man/assets/txt/version.txt
help2man/external/__init__.py
help2man/external/__main__.py
help2man/external/shtab/__init__.py
help2man/external/shtab/__main__.py
help2man/ui/__init__.py
help2man/ui/cli.py
help2man-0.0.9.data/data/share/bash-completion/completions/help2man
help2man-0.0.9.data/data/share/man/man1/help2man.1
help2man-0.0.9.data/data/share/zsh/site-functions/_help2man
help2man-0.0.9.dist-info/LICENSE
help2man-0.0.9.dist-info/METADATA
help2man-0.0.9.dist-info/WHEEL
help2man-0.0.9.dist-info/entry_points.txt
help2man-0.0.9.dist-info/top_level.txt
help2man-0.0.9.dist-info/RECORD
