Metadata-Version: 2.1
Name: help2man
Version: 0.0.9
Summary: Convert --help and --version to man page.
Author-email: Wu Zhenyu <wuzhenyu@ustc.edu>
License: GPL v3
Project-URL: Homepage, https://help2man.readthedocs.io
Project-URL: Download, https://github.com/Freed-Wu/help2man/releases
Project-URL: Bug Report, https://github.com/Freed-Wu/help2man/issues
Project-URL: Source, https://github.com/Freed-Wu/help2man
Keywords: help2man,man
Classifier: Development Status :: 3 - Alpha
Classifier: Intended Audience :: Developers
Classifier: Topic :: Software Development :: Build Tools
Classifier: License :: OSI Approved :: GNU General Public License v3 (GPLv3)
Classifier: Operating System :: Microsoft :: Windows
Classifier: Operating System :: POSIX
Classifier: Operating System :: Unix
Classifier: Operating System :: MacOS
Classifier: Programming Language :: Python :: 3 :: Only
Classifier: Programming Language :: Python :: 3
Classifier: Programming Language :: Python :: 3.9
Classifier: Programming Language :: Python :: 3.10
Classifier: Programming Language :: Python :: 3.11
Requires-Python: >=3.9
License-File: LICENSE
Requires-Dist: jinja2
Provides-Extra: dev
Requires-Dist: pre-commit ; extra == 'dev'
Requires-Dist: pytest-cov ; extra == 'dev'
Requires-Dist: shtab ; extra == 'dev'
Requires-Dist: tomli ; extra == 'dev'
